gokart_core_py.pypy37-pp73-x86_64-linux-gnu.so
gokart_core/__init__.py
gokartcorelujobi-0.0.37.dist-info/WHEEL
gokartcorelujobi-0.0.37.dist-info/top_level.txt
gokartcorelujobi-0.0.37.dist-info/RECORD
gokartcorelujobi-0.0.37.dist-info/LICENSE.md
gokartcorelujobi-0.0.37.dist-info/METADATA
