Metadata-Version: 2.1
Name: gokartcorelujobi
Version: 0.0.37
Summary: UNKNOWN
Home-page: https://github.com/idsc-frazzoli/gokart-core
Author: IDSC Frazzoli
Author-email: idscgokart@gmail.com
License: UNKNOWN
Platform: UNKNOWN
License-File: LICENSE.md
